quart_compress/__init__.py
quart_compress/quart_compress.py
quart_compress/typing.py
quart_compress2-1.1.0.dist-info/LICENSE
quart_compress2-1.1.0.dist-info/WHEEL
quart_compress2-1.1.0.dist-info/METADATA
quart_compress2-1.1.0.dist-info/RECORD
