Metadata-Version: 2.1
Name: quart-compress2
Version: 1.1.0
Summary: Quart-Compress.
Home-page: https://github.com/DahlitzFlorian/quart-compress
License: UNKNOWN
Author: Florian Dahlitz
Author-email: f2dahlitz@freenet.de
Requires-Python: >=3.7
Classifier: License :: OSI Approved :: MIT License
Requires-Dist: quart
